{
    "asset": {
        "format": "jpg",
        "id": "13c229bdc93791b3f6d61c47143592a9",
        "name": "lv_0_20211105223236_067.jpg",
        "path": "file:C:/Users/%E7%BD%97%E6%B2%9B/Desktop/3838/3and8/lv_0_20211105223236_067.jpg",
        "size": {
            "width": 224,
            "height": 224
        },
        "state": 2,
        "type": 1
    },
    "regions": [
        {
            "id": "moB3v_Aek",
            "type": "RECTANGLE",
            "tags": [
                "8"
            ],
            "boundingBox": {
                "height": 110.28528015219986,
                "width": 83.80052678419167,
                "left": 22.57995955192701,
                "top": 61.52615135786153
            },
            "points": [
                {
                    "x": 22.57995955192701,
                    "y": 61.52615135786153
                },
                {
                    "x": 106.3804863361187,
                    "y": 61.52615135786153
                },
                {
                    "x": 106.3804863361187,
                    "y": 171.8114315100614
                },
                {
                    "x": 22.57995955192701,
                    "y": 171.8114315100614
                }
            ]
        }
    ],
    "version": "2.2.0"
}