{
    "asset": {
        "format": "jpg",
        "id": "702f3e149a85a7a2a1d011d52924c6e3",
        "name": "lv_0_20211106164938_118.jpg",
        "path": "file:C:/Users/%E7%BD%97%E6%B2%9B/Desktop/3or8/3or8in/lv_0_20211106164938_118.jpg",
        "size": {
            "width": 224,
            "height": 224
        },
        "state": 2,
        "type": 1
    },
    "regions": [
        {
            "id": "F7SyvCYtI",
            "type": "RECTANGLE",
            "tags": [
                "3"
            ],
            "boundingBox": {
                "height": 93.81718963165072,
                "width": 79.75989085948159,
                "left": 78.8431105047749,
                "top": 79.75989085948159
            },
            "points": [
                {
                    "x": 78.8431105047749,
                    "y": 79.75989085948159
                },
                {
                    "x": 158.60300136425647,
                    "y": 79.75989085948159
                },
                {
                    "x": 158.60300136425647,
                    "y": 173.5770804911323
                },
                {
                    "x": 78.8431105047749,
                    "y": 173.5770804911323
                }
            ]
        }
    ],
    "version": "2.2.0"
}