{
    "asset": {
        "format": "jpg",
        "id": "877ecec9316a3242348c5c766cdfda5f",
        "name": "lv_0_20211105223236_221.jpg",
        "path": "file:C:/Users/%E7%BD%97%E6%B2%9B/Desktop/3838/3and8/lv_0_20211105223236_221.jpg",
        "size": {
            "width": 224,
            "height": 224
        },
        "state": 2,
        "type": 1
    },
    "regions": [
        {
            "id": "AUESn_6SY",
            "type": "RECTANGLE",
            "tags": [
                "8"
            ],
            "boundingBox": {
                "height": 185.3933551783126,
                "width": 133.5103824714359,
                "left": 37.92754385871419,
                "top": 8.828256562819748
            },
            "points": [
                {
                    "x": 37.92754385871419,
                    "y": 8.828256562819748
                },
                {
                    "x": 171.43792633015008,
                    "y": 8.828256562819748
                },
                {
                    "x": 171.43792633015008,
                    "y": 194.22161174113234
                },
                {
                    "x": 37.92754385871419,
                    "y": 194.22161174113234
                }
            ]
        }
    ],
    "version": "2.2.0"
}