{
    "asset": {
        "format": "jpg",
        "id": "e6f5165c9b2893298375c4247aff4cda",
        "name": "lv_0_20211105223236_197.jpg",
        "path": "file:C:/Users/%E7%BD%97%E6%B2%9B/Desktop/3838/3and8/lv_0_20211105223236_197.jpg",
        "size": {
            "width": 224,
            "height": 224
        },
        "state": 2,
        "type": 1
    },
    "regions": [
        {
            "id": "NhmB2etuT",
            "type": "RECTANGLE",
            "tags": [
                "8"
            ],
            "boundingBox": {
                "height": 105.80325063416609,
                "width": 76.4662559686221,
                "left": 70.93164595412688,
                "top": 49.03077104472203
            },
            "points": [
                {
                    "x": 70.93164595412688,
                    "y": 49.03077104472203
                },
                {
                    "x": 147.39790192274899,
                    "y": 49.03077104472203
                },
                {
                    "x": 147.39790192274899,
                    "y": 154.83402167888812
                },
                {
                    "x": 70.93164595412688,
                    "y": 154.83402167888812
                }
            ]
        }
    ],
    "version": "2.2.0"
}